biliffm4s/__init__.py
biliffm4s/biliffm4s.py
biliffm4s/ffmpeg/avcodec-59.dll
biliffm4s/ffmpeg/avdevice-59.dll
biliffm4s/ffmpeg/avfilter-8.dll
biliffm4s/ffmpeg/avformat-59.dll
biliffm4s/ffmpeg/avutil-57.dll
biliffm4s/ffmpeg/ffmpeg.exe
biliffm4s/ffmpeg/ffplay.exe
biliffm4s/ffmpeg/ffprobe.exe
biliffm4s/ffmpeg/m4s合并.txt
biliffm4s/ffmpeg/postproc-56.dll
biliffm4s/ffmpeg/swresample-4.dll
biliffm4s/ffmpeg/swscale-6.dll
biliffm4s/ffmpeg/linux/ffmpeg
biliffm4s/ffmpeg/mac/ffmpeg
biliffm4s/ffmpeg/win/avcodec-59.dll
biliffm4s/ffmpeg/win/avdevice-59.dll
biliffm4s/ffmpeg/win/avfilter-8.dll
biliffm4s/ffmpeg/win/avformat-59.dll
biliffm4s/ffmpeg/win/avutil-57.dll
biliffm4s/ffmpeg/win/ffmpeg.exe
biliffm4s/ffmpeg/win/ffplay.exe
biliffm4s/ffmpeg/win/ffprobe.exe
biliffm4s/ffmpeg/win/m4s合并.txt
biliffm4s/ffmpeg/win/postproc-56.dll
biliffm4s/ffmpeg/win/swresample-4.dll
biliffm4s/ffmpeg/win/swscale-6.dll
biliffm4s-1.5.dist-info/METADATA
biliffm4s-1.5.dist-info/WHEEL
biliffm4s-1.5.dist-info/top_level.txt
biliffm4s-1.5.dist-info/RECORD
