Metadata-Version: 2.1
Name: biliffm4s
Version: 1.5
Summary: biliffm4s: A tool to merge Bilibili cached .m4s files into .mp4
Home-page: https://github.com/Water-Run/-m4s-Python-biliffm4s
Author: WaterRun
Author-email: 2263633954@qq.com
Classifier: Programming Language :: Python :: 3
Classifier: Programming Language :: Python :: 3.6
Classifier: Programming Language :: Python :: 3.7
Classifier: Programming Language :: Python :: 3.8
Classifier: Programming Language :: Python :: 3.9
Classifier: Programming Language :: Python :: 3.10
Classifier: Programming Language :: Python :: 3.11
Classifier: License :: OSI Approved :: MIT License
Classifier: Operating System :: Microsoft :: Windows
Classifier: Operating System :: POSIX :: Linux
Classifier: Operating System :: MacOS
Classifier: Operating System :: OS Independent
Classifier: Environment :: Console
Requires-Python: >=3.6
